ptnad/__init__.py
ptnad/auth.py
ptnad/client.py
ptnad/exceptions.py
ptnad/py.typed
ptnad/api/__init__.py
ptnad/api/bql.py
ptnad/api/filters.py
ptnad/api/hosts.py
ptnad/api/monitoring.py
ptnad/api/replists.py
ptnad/api/sensors.py
ptnad/api/signatures.py
ptnad/api/sources.py
ptnad/api/variables.py
ptnad_client-0.2.1.dist-info/METADATA
ptnad_client-0.2.1.dist-info/WHEEL
ptnad_client-0.2.1.dist-info/licenses/LICENSE
ptnad_client-0.2.1.dist-info/RECORD
