Metadata-Version: 2.4
Name: ptnad-client
Version: 0.2.1
Summary: Python library for interacting with the PT NAD API
Project-URL: Homepage, https://github.com/Security-Experts-Community/ptnad-client
Project-URL: Documentation, https://security-experts-community.github.io/ptnad-client
Project-URL: Repository, https://github.com/Security-Experts-Community/ptnad-client
Project-URL: Issues, https://github.com/Security-Experts-Community/ptnad-client/issues
Author: Andrey Tyulenev
License-Expression: MIT
License-File: LICENSE
Classifier: License :: OSI Approved :: MIT License
Classifier: Programming Language :: Python :: 3
Requires-Python: >=3.12
Requires-Dist: mkdocs
Requires-Dist: mkdocs-material
Requires-Dist: mkdocs-static-i18n
Requires-Dist: mkdocstrings-python
Requires-Dist: requests>=2.32.3
Requires-Dist: termynal
